{"schema_version":"0.1","session_id":"58b09396960bb17904c6b53efee695e2","remote_ip":null,"first_seen":"2026-06-20T22:06:59Z","last_seen":"2026-06-20T22:07:02Z","request_count":23,"signals":{"network":[{"schema_version":"0.1","session_id":"58b09396960bb17904c6b53efee695e2","layer":"network","kind":"accept_language_primary","value":"en","source":"edge","observed_at":"2026-06-20T22:07:02Z"},{"schema_version":"0.1","session_id":"58b09396960bb17904c6b53efee695e2","layer":"network","kind":"h2","value":"1:65536;2:0;4:131072;5:16384|12517377|0|m,p,a,s","source":"edge","observed_at":"2026-06-20T22:07:02Z"},{"schema_version":"0.1","session_id":"58b09396960bb17904c6b53efee695e2","layer":"network","kind":"h2_browser_hint","value":"firefox","source":"edge","observed_at":"2026-06-20T22:07:02Z"},{"schema_version":"0.1","session_id":"58b09396960bb17904c6b53efee695e2","layer":"network","kind":"h2_settings_hint","value":"firefox","source":"edge","observed_at":"2026-06-20T22:07:02Z"},{"schema_version":"0.1","session_id":"58b09396960bb17904c6b53efee695e2","layer":"network","kind":"http_user_agent","value":"Mozilla/5.0 (X11; Linux x86_64; rv:135.0) Gecko/20100101 Firefox/135.0","source":"edge","observed_at":"2026-06-20T22:07:02Z"},{"schema_version":"0.1","session_id":"58b09396960bb17904c6b53efee695e2","layer":"network","kind":"ja3","value":"d87a30a5782a73a83c1544bb06332780","source":"edge","observed_at":"2026-06-20T22:07:02Z"},{"schema_version":"0.1","session_id":"58b09396960bb17904c6b53efee695e2","layer":"network","kind":"ja4","value":"t13d1717h2_5b57614c22b0_3cbfd9057e0d","source":"edge","observed_at":"2026-06-20T22:07:02Z"},{"schema_version":"0.1","session_id":"58b09396960bb17904c6b53efee695e2","layer":"network","kind":"ja4_browser_hint","value":"firefox","source":"edge","observed_at":"2026-06-20T22:07:02Z"},{"schema_version":"0.1","session_id":"58b09396960bb17904c6b53efee695e2","layer":"network","kind":"observed_ip","value":"172.22.0.4","source":"edge","observed_at":"2026-06-20T22:07:02Z"},{"schema_version":"0.1","session_id":"58b09396960bb17904c6b53efee695e2","layer":"network","kind":"quic_observed","value":true,"source":"edge","observed_at":"2026-06-20T22:07:02Z"},{"schema_version":"0.1","session_id":"58b09396960bb17904c6b53efee695e2","layer":"network","kind":"tcp_kernel","value":"linux","source":"edge","observed_at":"2026-06-20T22:07:02Z"},{"schema_version":"0.1","session_id":"58b09396960bb17904c6b53efee695e2","layer":"network","kind":"ua_kernel","value":"linux","source":"edge","observed_at":"2026-06-20T22:07:02Z"},{"schema_version":"0.1","session_id":"58b09396960bb17904c6b53efee695e2","layer":"network","kind":"observed_ip_seen","value":["172.22.0.4"],"source":"edge","observed_at":"2026-06-20T22:06:59Z"},{"schema_version":"0.1","session_id":"58b09396960bb17904c6b53efee695e2","layer":"network","kind":"ua_seen","value":["Mozilla/5.0 (X11; Linux x86_64; rv:135.0) Gecko/20100101 Firefox/135.0"],"source":"edge","observed_at":"2026-06-20T22:06:59Z"}],"browser":[{"schema_version":"0.1","session_id":"58b09396960bb17904c6b53efee695e2","layer":"browser","kind":"color_depth","value":24,"source":"collector","observed_at":"2026-06-20T22:07:01.821000Z"},{"schema_version":"0.1","session_id":"58b09396960bb17904c6b53efee695e2","layer":"browser","kind":"fp_hash","value":"a354adf4","source":"collector","observed_at":"2026-06-20T22:07:01.821000Z"},{"schema_version":"0.1","session_id":"58b09396960bb17904c6b53efee695e2","layer":"browser","kind":"hardware_concurrency","value":16,"source":"collector","observed_at":"2026-06-20T22:07:01.821000Z"},{"schema_version":"0.1","session_id":"58b09396960bb17904c6b53efee695e2","layer":"browser","kind":"media_devices_empty","value":true,"source":"collector","observed_at":"2026-06-20T22:07:01.821000Z"},{"schema_version":"0.1","session_id":"58b09396960bb17904c6b53efee695e2","layer":"browser","kind":"nav_language_primary","value":"en","source":"collector","observed_at":"2026-06-20T22:07:01.821000Z"},{"schema_version":"0.1","session_id":"58b09396960bb17904c6b53efee695e2","layer":"browser","kind":"nav_platform_os","value":"Linux","source":"collector","observed_at":"2026-06-20T22:07:01.821000Z"},{"schema_version":"0.1","session_id":"58b09396960bb17904c6b53efee695e2","layer":"browser","kind":"oscpu_os","value":"Linux","source":"collector","observed_at":"2026-06-20T22:07:01.821000Z"},{"schema_version":"0.1","session_id":"58b09396960bb17904c6b53efee695e2","layer":"browser","kind":"plugins_count","value":5,"source":"collector","observed_at":"2026-06-20T22:07:01.821000Z"},{"schema_version":"0.1","session_id":"58b09396960bb17904c6b53efee695e2","layer":"browser","kind":"productsub_render","value":"gecko","source":"collector","observed_at":"2026-06-20T22:07:01.821000Z"},{"schema_version":"0.1","session_id":"58b09396960bb17904c6b53efee695e2","layer":"browser","kind":"screen_resolution","value":"1707x960","source":"collector","observed_at":"2026-06-20T22:07:01.821000Z"},{"schema_version":"0.1","session_id":"58b09396960bb17904c6b53efee695e2","layer":"browser","kind":"ua_browser","value":"firefox","source":"collector","observed_at":"2026-06-20T22:07:01.821000Z"},{"schema_version":"0.1","session_id":"58b09396960bb17904c6b53efee695e2","layer":"browser","kind":"ua_engine","value":"firefox","source":"collector","observed_at":"2026-06-20T22:07:01.821000Z"},{"schema_version":"0.1","session_id":"58b09396960bb17904c6b53efee695e2","layer":"browser","kind":"ua_platform","value":"Linux","source":"collector","observed_at":"2026-06-20T22:07:01.821000Z"},{"schema_version":"0.1","session_id":"58b09396960bb17904c6b53efee695e2","layer":"browser","kind":"ua_render","value":"gecko","source":"collector","observed_at":"2026-06-20T22:07:01.821000Z"},{"schema_version":"0.1","session_id":"58b09396960bb17904c6b53efee695e2","layer":"browser","kind":"vendor_engine","value":"firefox","source":"collector","observed_at":"2026-06-20T22:07:01.821000Z"},{"schema_version":"0.1","session_id":"58b09396960bb17904c6b53efee695e2","layer":"browser","kind":"voices_empty","value":true,"source":"collector","observed_at":"2026-06-20T22:07:01.821000Z"},{"schema_version":"0.1","session_id":"58b09396960bb17904c6b53efee695e2","layer":"browser","kind":"webdriver","value":false,"source":"collector","observed_at":"2026-06-20T22:07:01.821000Z"},{"schema_version":"0.1","session_id":"58b09396960bb17904c6b53efee695e2","layer":"browser","kind":"webgl2_missing","value":true,"source":"collector","observed_at":"2026-06-20T22:07:01.821000Z"},{"schema_version":"0.1","session_id":"58b09396960bb17904c6b53efee695e2","layer":"browser","kind":"webgpu_absent","value":true,"source":"collector","observed_at":"2026-06-20T22:07:01.821000Z"},{"schema_version":"0.1","session_id":"58b09396960bb17904c6b53efee695e2","layer":"browser","kind":"webrtc_unavailable","value":true,"source":"collector","observed_at":"2026-06-20T22:07:01.821000Z"},{"schema_version":"0.1","session_id":"58b09396960bb17904c6b53efee695e2","layer":"browser","kind":"fp_seen","value":{"nav_platform_os":["Linux"],"hardware_concurrency":["16"]},"source":"collector","observed_at":"2026-06-20T22:07:01.821000Z"}],"behavioral":[{"schema_version":"0.1","session_id":"58b09396960bb17904c6b53efee695e2","layer":"behavioral","kind":"coalesced_events_absent","value":true,"source":"collector","observed_at":"2026-06-20T22:07:01.821000Z"},{"schema_version":"0.1","session_id":"58b09396960bb17904c6b53efee695e2","layer":"behavioral","kind":"keystroke_entropy","value":1,"source":"collector","observed_at":"2026-06-20T22:07:01.821000Z"},{"schema_version":"0.1","session_id":"58b09396960bb17904c6b53efee695e2","layer":"behavioral","kind":"mouse_entropy","value":0.8428244794243289,"source":"collector","observed_at":"2026-06-20T22:07:01.821000Z"},{"schema_version":"0.1","session_id":"58b09396960bb17904c6b53efee695e2","layer":"behavioral","kind":"mouse_straightness","value":0.169578690921734,"source":"collector","observed_at":"2026-06-20T22:07:01.821000Z"},{"schema_version":"0.1","session_id":"58b09396960bb17904c6b53efee695e2","layer":"behavioral","kind":"mouse_velocity_cv","value":0.8513088573113791,"source":"collector","observed_at":"2026-06-20T22:07:01.821000Z"},{"schema_version":"0.1","session_id":"58b09396960bb17904c6b53efee695e2","layer":"behavioral","kind":"pause_ratio","value":0.14925373134328357,"source":"collector","observed_at":"2026-06-20T22:07:01.821000Z"},{"schema_version":"0.1","session_id":"58b09396960bb17904c6b53efee695e2","layer":"behavioral","kind":"pointer_event_count","value":68,"source":"collector","observed_at":"2026-06-20T22:07:01.821000Z"},{"schema_version":"0.1","session_id":"58b09396960bb17904c6b53efee695e2","layer":"behavioral","kind":"power_law_exponent","value":0.35364981496241304,"source":"collector","observed_at":"2026-06-20T22:07:01.821000Z"},{"schema_version":"0.1","session_id":"58b09396960bb17904c6b53efee695e2","layer":"behavioral","kind":"submovement_count","value":20,"source":"collector","observed_at":"2026-06-20T22:07:01.821000Z"},{"schema_version":"0.1","session_id":"58b09396960bb17904c6b53efee695e2","layer":"behavioral","kind":"trace_hash","value":"bb2d5770","source":"collector","observed_at":"2026-06-20T22:07:01.821000Z"},{"schema_version":"0.1","session_id":"58b09396960bb17904c6b53efee695e2","layer":"behavioral","kind":"trace_seen","value":{"bb2d5770":["2026-06-20T22:07:01.821000+00:00"]},"source":"collector","observed_at":"2026-06-20T22:07:01.821000Z"}],"reputation":[]}}
